tests/__init__.py
tests/test_vtapi3_analyses.py
tests/test_vtapi3_base.py
tests/test_vtapi3_domains.py
tests/test_vtapi3_files.py
tests/test_vtapi3_ip.py
tests/test_vtapi3_main.py
tests/test_vtapi3_urls.py
vtapi3/__init__.py
vtapi3/__main__.py
vtapi3/vtapi3.py
vtapi3/vtapi3analyses.py
vtapi3/vtapi3base.py
vtapi3/vtapi3domains.py
vtapi3/vtapi3error.py
vtapi3/vtapi3files.py
vtapi3/vtapi3ipaddresses.py
vtapi3/vtapi3urls.py
vtapi3-1.2.1.dist-info/LICENSE
vtapi3-1.2.1.dist-info/METADATA
vtapi3-1.2.1.dist-info/WHEEL
vtapi3-1.2.1.dist-info/top_level.txt
vtapi3-1.2.1.dist-info/RECORD
