Metadata-Version: 2.1
Name: vtapi3
Version: 1.2.1
Summary: VirusTotal API
Home-page: https://github.com/drobotun/virustotalapi3/
Author: Evgeny Drobotun
Author-email: drobotun@xakep.ru
License: MIT
Project-URL: Documentation, https://virustotalapi3.readthedocs.io/
Project-URL: Source, https://github.com/drobotun/virustotalapi3/
Keywords: virustotal api
Platform: UNKNOWN
Classifier: Development Status :: 5 - Production/Stable
Classifier: Intended Audience :: Developers
Classifier: License :: OSI Approved :: MIT License
Classifier: Programming Language :: Python :: 3.4
Classifier: Programming Language :: Python :: 3.7
Requires-Dist: requests (>=2.22.0)
